<?xml version="1.0" encoding="UTF-8" ?>
<!DOCTYPE mapper PUBLIC "-//mybatis.org//DTD Mapper 3.0//EN" "http://mybatis.org/dtd/mybatis-3-mapper.dtd" >
<mapper namespace="com.mt.iv.common.dao.IvScrapMatBillSubMapper" >
  <resultMap id="BaseResultMap" type="com.mt.iv.common.model.IvScrapMatBillSub" >
    <!--
      WARNING - @mbggenerated
      This element is automatically generated by MyBatis Generator, do not modify.
      This element was generated on Thu Nov 30 09:32:25 CST 2017.
    -->
    <id column="id" property="id" jdbcType="BIGINT" />
    <result column="scrap_id" property="scrapId" jdbcType="BIGINT" />
    <result column="deal_flag" property="dealFlag" jdbcType="TINYINT" />
    <result column="mat_id" property="matId" jdbcType="BIGINT" />
    <result column="mat_no" property="matNo" jdbcType="VARCHAR" />
    <result column="mat_desc" property="matDesc" jdbcType="VARCHAR" />
    <result column="mat_type_id" property="matTypeId" jdbcType="BIGINT" />
    <result column="mat_type_name" property="matTypeName" jdbcType="VARCHAR" />
    <result column="mat_model" property="matModel" jdbcType="VARCHAR" />
    <result column="unit" property="unit" jdbcType="VARCHAR" />
    <result column="quantity" property="quantity" jdbcType="DECIMAL" />
    <result column="weight" property="weight" jdbcType="DECIMAL" />
    <result column="reason" property="reason" jdbcType="VARCHAR" />
    <result column="created_at" property="createdAt" jdbcType="TIMESTAMP" />
    <result column="updated_at" property="updatedAt" jdbcType="TIMESTAMP" />
    <result column="status" property="status" jdbcType="TINYINT" />
  </resultMap>
  <sql id="Base_Column_List" >
    <!--
      WARNING - @mbggenerated
      This element is automatically generated by MyBatis Generator, do not modify.
      This element was generated on Thu Nov 30 09:32:25 CST 2017.
    -->
    id, scrap_id, deal_flag, mat_id, mat_no, mat_desc, mat_type_id, mat_type_name, mat_model, 
    unit, quantity, weight, reason, created_at, updated_at, status
  </sql>
  <select id="selectByPrimaryKey" resultMap="BaseResultMap" parameterType="java.lang.Long" >
    <!--
      WARNING - @mbggenerated
      This element is automatically generated by MyBatis Generator, do not modify.
      This element was generated on Thu Nov 30 09:32:25 CST 2017.
    -->
    select 
    <include refid="Base_Column_List" />
    from iv_scrap_mat_bill_sub
    where id = #{id,jdbcType=BIGINT}
  </select>
  <delete id="deleteByPrimaryKey" parameterType="java.lang.Long" >
    <!--
      WARNING - @mbggenerated
      This element is automatically generated by MyBatis Generator, do not modify.
      This element was generated on Thu Nov 30 09:32:25 CST 2017.
    -->
    delete from iv_scrap_mat_bill_sub
    where id = #{id,jdbcType=BIGINT}
  </delete>
  <insert id="insert" parameterType="com.mt.iv.common.model.IvScrapMatBillSub" >
    <!--
      WARNING - @mbggenerated
      This element is automatically generated by MyBatis Generator, do not modify.
      This element was generated on Thu Nov 30 09:32:25 CST 2017.
    -->
    insert into iv_scrap_mat_bill_sub (id, scrap_id, deal_flag, 
      mat_id, mat_no, mat_desc, 
      mat_type_id, mat_type_name, mat_model, 
      unit, quantity, weight, 
      reason, created_at, updated_at, 
      status)
    values (#{id,jdbcType=BIGINT}, #{scrapId,jdbcType=BIGINT}, #{dealFlag,jdbcType=TINYINT}, 
      #{matId,jdbcType=BIGINT}, #{matNo,jdbcType=VARCHAR}, #{matDesc,jdbcType=VARCHAR}, 
      #{matTypeId,jdbcType=BIGINT}, #{matTypeName,jdbcType=VARCHAR}, #{matModel,jdbcType=VARCHAR}, 
      #{unit,jdbcType=VARCHAR}, #{quantity,jdbcType=DECIMAL}, #{weight,jdbcType=DECIMAL}, 
      #{reason,jdbcType=VARCHAR}, #{createdAt,jdbcType=TIMESTAMP}, #{updatedAt,jdbcType=TIMESTAMP}, 
      #{status,jdbcType=TINYINT})
  </insert>
  <insert id="insertSelective" parameterType="com.mt.iv.common.model.IvScrapMatBillSub" >
    <!--
      WARNING - @mbggenerated
      This element is automatically generated by MyBatis Generator, do not modify.
      This element was generated on Thu Nov 30 09:32:25 CST 2017.
    -->
    insert into iv_scrap_mat_bill_sub
    <trim prefix="(" suffix=")" suffixOverrides="," >
      <if test="id != null" >
        id,
      </if>
      <if test="scrapId != null" >
        scrap_id,
      </if>
      <if test="dealFlag != null" >
        deal_flag,
      </if>
      <if test="matId != null" >
        mat_id,
      </if>
      <if test="matNo != null" >
        mat_no,
      </if>
      <if test="matDesc != null" >
        mat_desc,
      </if>
      <if test="matTypeId != null" >
        mat_type_id,
      </if>
      <if test="matTypeName != null" >
        mat_type_name,
      </if>
      <if test="matModel != null" >
        mat_model,
      </if>
      <if test="unit != null" >
        unit,
      </if>
      <if test="quantity != null" >
        quantity,
      </if>
      <if test="weight != null" >
        weight,
      </if>
      <if test="reason != null" >
        reason,
      </if>
      <if test="createdAt != null" >
        created_at,
      </if>
      <if test="updatedAt != null" >
        updated_at,
      </if>
      <if test="status != null" >
        status,
      </if>
    </trim>
    <trim prefix="values (" suffix=")" suffixOverrides="," >
      <if test="id != null" >
        #{id,jdbcType=BIGINT},
      </if>
      <if test="scrapId != null" >
        #{scrapId,jdbcType=BIGINT},
      </if>
      <if test="dealFlag != null" >
        #{dealFlag,jdbcType=TINYINT},
      </if>
      <if test="matId != null" >
        #{matId,jdbcType=BIGINT},
      </if>
      <if test="matNo != null" >
        #{matNo,jdbcType=VARCHAR},
      </if>
      <if test="matDesc != null" >
        #{matDesc,jdbcType=VARCHAR},
      </if>
      <if test="matTypeId != null" >
        #{matTypeId,jdbcType=BIGINT},
      </if>
      <if test="matTypeName != null" >
        #{matTypeName,jdbcType=VARCHAR},
      </if>
      <if test="matModel != null" >
        #{matModel,jdbcType=VARCHAR},
      </if>
      <if test="unit != null" >
        #{unit,jdbcType=VARCHAR},
      </if>
      <if test="quantity != null" >
        #{quantity,jdbcType=DECIMAL},
      </if>
      <if test="weight != null" >
        #{weight,jdbcType=DECIMAL},
      </if>
      <if test="reason != null" >
        #{reason,jdbcType=VARCHAR},
      </if>
      <if test="createdAt != null" >
        #{createdAt,jdbcType=TIMESTAMP},
      </if>
      <if test="updatedAt != null" >
        #{updatedAt,jdbcType=TIMESTAMP},
      </if>
      <if test="status != null" >
        #{status,jdbcType=TINYINT},
      </if>
    </trim>
  </insert>
  <update id="updateByPrimaryKeySelective" parameterType="com.mt.iv.common.model.IvScrapMatBillSub" >
    <!--
      WARNING - @mbggenerated
      This element is automatically generated by MyBatis Generator, do not modify.
      This element was generated on Thu Nov 30 09:32:25 CST 2017.
    -->
    update iv_scrap_mat_bill_sub
    <set >
      <if test="scrapId != null" >
        scrap_id = #{scrapId,jdbcType=BIGINT},
      </if>
      <if test="dealFlag != null" >
        deal_flag = #{dealFlag,jdbcType=TINYINT},
      </if>
      <if test="matId != null" >
        mat_id = #{matId,jdbcType=BIGINT},
      </if>
      <if test="matNo != null" >
        mat_no = #{matNo,jdbcType=VARCHAR},
      </if>
      <if test="matDesc != null" >
        mat_desc = #{matDesc,jdbcType=VARCHAR},
      </if>
      <if test="matTypeId != null" >
        mat_type_id = #{matTypeId,jdbcType=BIGINT},
      </if>
      <if test="matTypeName != null" >
        mat_type_name = #{matTypeName,jdbcType=VARCHAR},
      </if>
      <if test="matModel != null" >
        mat_model = #{matModel,jdbcType=VARCHAR},
      </if>
      <if test="unit != null" >
        unit = #{unit,jdbcType=VARCHAR},
      </if>
      <if test="quantity != null" >
        quantity = #{quantity,jdbcType=DECIMAL},
      </if>
      <if test="weight != null" >
        weight = #{weight,jdbcType=DECIMAL},
      </if>
      <if test="reason != null" >
        reason = #{reason,jdbcType=VARCHAR},
      </if>
      <if test="createdAt != null" >
        created_at = #{createdAt,jdbcType=TIMESTAMP},
      </if>
      <if test="updatedAt != null" >
        updated_at = #{updatedAt,jdbcType=TIMESTAMP},
      </if>
      <if test="status != null" >
        status = #{status,jdbcType=TINYINT},
      </if>
    </set>
    where id = #{id,jdbcType=BIGINT}
  </update>
  <update id="updateByPrimaryKey" parameterType="com.mt.iv.common.model.IvScrapMatBillSub" >
    <!--
      WARNING - @mbggenerated
      This element is automatically generated by MyBatis Generator, do not modify.
      This element was generated on Thu Nov 30 09:32:25 CST 2017.
    -->
    update iv_scrap_mat_bill_sub
    set scrap_id = #{scrapId,jdbcType=BIGINT},
      deal_flag = #{dealFlag,jdbcType=TINYINT},
      mat_id = #{matId,jdbcType=BIGINT},
      mat_no = #{matNo,jdbcType=VARCHAR},
      mat_desc = #{matDesc,jdbcType=VARCHAR},
      mat_type_id = #{matTypeId,jdbcType=BIGINT},
      mat_type_name = #{matTypeName,jdbcType=VARCHAR},
      mat_model = #{matModel,jdbcType=VARCHAR},
      unit = #{unit,jdbcType=VARCHAR},
      quantity = #{quantity,jdbcType=DECIMAL},
      weight = #{weight,jdbcType=DECIMAL},
      reason = #{reason,jdbcType=VARCHAR},
      created_at = #{createdAt,jdbcType=TIMESTAMP},
      updated_at = #{updatedAt,jdbcType=TIMESTAMP},
      status = #{status,jdbcType=TINYINT}
    where id = #{id,jdbcType=BIGINT}
  </update>


    <!-- wendy添加-->

  <select  id="selectScrapMatBillSubDetail"  resultType="map"  parameterType="java.lang.Long">
          SELECT deal_flag, id AS detail_id, mat_desc, mat_id, mat_model
        , mat_no, mat_type_id, mat_type_name, quantity, reason
        , unit, weight, store_room_id, store_house_id, store_house_name
        , store_room_name, price, stock_qty
    FROM iv_scrap_mat_bill_sub
    WHERE scrap_id = #{scrap_id}
        AND status = 1
  </select>

    <!--新增报废单详情表-->
    <insert id="addScrapMatBillSub" parameterType="map" useGeneratedKeys="true" keyProperty="id" keyColumn="id">
        <selectKey resultType="int" order="AFTER" keyProperty="id">
            SELECT LAST_INSERT_ID() as id
        </selectKey>
        insert into iv_scrap_mat_bill_sub
        <trim prefix="(" suffix=")" suffixOverrides="," >
            <if test="deal_flag != null and deal_flag !=''" >
                deal_flag,
            </if>
            <if test="mat_id != null and mat_id !=''" >
                mat_id,
            </if>
            <if test="mat_no != null and mat_no !=''" >
                mat_no,
            </if>
            <if test="mat_desc != null and mat_desc !=''" >
                mat_desc,
            </if>
            <if test="mat_type_id != null and mat_type_id !=''"  >
                mat_type_id,
            </if>
            <if test="mat_type_name != null and mat_type_name !=''" >
                mat_type_name,
            </if>
            <if test="mat_model != null and mat_model !=''" >
                mat_model,
            </if>
            <if test="store_house_id != null  and  store_house_id!=''" >
                store_house_id,
            </if>
            <if test="store_house_name != null  and  store_house_name!=''" >
                store_house_name,
            </if>
            <if test="store_room_id != null  and  store_room_id!=''" >
                store_room_id,
            </if>
            <if test="store_room_name != null  and  store_room_name!=''" >
                store_room_name,
            </if>
            <if test="unit != null and unit !=''" >
                unit,
            </if>
            <if test="quantity != null and quantity !=''" >
                quantity,
            </if>
            <if test="weight != null and weight !=''" >
                weight,
            </if>
            <if test="reason != null and reason !=''" >
                reason,
            </if>
            <if test="scrap_id != null and scrap_id !=''" >
                scrap_id,
            </if>
        </trim>
        <trim prefix="values (" suffix=")" suffixOverrides="," >
            <if test="deal_flag != null and deal_flag !=''" >
                #{deal_flag,jdbcType=TINYINT},
            </if>
            <if test="mat_id != null and mat_id !=''" >
                #{mat_id,jdbcType=BIGINT},
            </if>
            <if test="mat_no != null and mat_no !=''" >
                #{mat_no,jdbcType=VARCHAR},
            </if>
            <if test="mat_desc != null and mat_desc !=''" >
                #{mat_desc,jdbcType=VARCHAR},
            </if>
            <if test="mat_type_id != null and mat_type_id !=''"  >
                #{mat_type_id,jdbcType=BIGINT},
            </if>
            <if test="mat_type_name != null and mat_type_name !=''" >
                #{mat_type_name,jdbcType=VARCHAR},
            </if>
            <if test="mat_model != null and mat_model !=''" >
                #{mat_model,jdbcType=VARCHAR},
            </if>
            <if test="store_house_id != null and store_house_id !=''" >
                #{store_house_id,jdbcType=BIGINT},
            </if>
            <if test="store_house_name != null and store_house_name !=''" >
                #{store_house_name,jdbcType=VARCHAR},
            </if>
            <if test="store_room_id != null and store_room_id !=''" >
                #{store_room_id,jdbcType=BIGINT},
            </if>
            <if test="store_room_name != null and store_room_name !=''" >
                #{store_room_name,jdbcType=VARCHAR},
            </if>
            <if test="unit != null and unit !=''" >
                #{unit,jdbcType=VARCHAR},
            </if>
            <if test="quantity != null and quantity !=''" >
                #{quantity,jdbcType=DECIMAL},
            </if>
            <if test="weight != null and weight !=''" >
                #{weight,jdbcType=DECIMAL},
            </if>
            <if test="reason != null and reason !=''" >
                #{reason,jdbcType=VARCHAR},
            </if>
            <if test="scrap_id != null and scrap_id!=''" >
                #{scrap_id,jdbcType=BIGINT},
            </if>
        </trim>
    </insert>

    <!--修改报废单详情表-->
    <update  id="updateScrapMatBillSub"  parameterType="map">
        update iv_scrap_mat_bill_sub
        <set >
            <if test="scrap_id != null and scrap_id !=''" >
                scrap_id = #{scrap_id,jdbcType=BIGINT},
            </if>
            <if test="deal_flag != null and deal_flag !=''" >
                deal_flag = #{deal_flag,jdbcType=TINYINT},
            </if>
            <if test="mat_id != null and mat_id !=''" >
                mat_id = #{mat_id,jdbcType=BIGINT},
            </if>
            <if test="mat_no != null and mat_no !=''" >
                mat_no = #{mat_no,jdbcType=VARCHAR},
            </if>
            <if test="mat_desc != null and mat_desc !=''" >
                mat_desc = #{mat_desc,jdbcType=VARCHAR},
            </if>
            <if test="mat_type_id != null and mat_type_id !=''"  >
                mat_type_id = #{mat_type_id,jdbcType=BIGINT},
            </if>
            <if test="mat_type_name != null and mat_type_name !=''" >
                mat_type_name = #{mat_type_name,jdbcType=VARCHAR},
            </if>
            <if test="mat_model != null and mat_model !=''" >
                mat_model = #{mat_model,jdbcType=VARCHAR},
            </if>
            <if test="store_house_id != null and store_house_id !=''" >
                store_house_id=#{store_house_id,jdbcType=BIGINT},
            </if>
            <if test="store_house_name != null and store_house_name !=''" >
                store_house_name=#{store_house_name,jdbcType=VARCHAR},
            </if>
            <if test="store_room_id != null and store_room_id !=''" >
                store_room_id=#{store_room_id,jdbcType=BIGINT},
            </if>
            <if test="store_room_name != null and store_room_name !=''" >
                store_room_name=#{store_room_name,jdbcType=VARCHAR},
            </if>
            <if test="unit != null and unit !=''" >
                unit = #{unit,jdbcType=VARCHAR},
            </if>
            <if test="quantity != null and quantity !=''" >
                quantity = #{quantity,jdbcType=DECIMAL},
            </if>
            <if test="stock_qty != null and stock_qty !=''" >
                stock_qty = #{stock_qty,jdbcType=DECIMAL},
            </if>
            <if test="weight != null and weight !=''" >
                weight = #{weight,jdbcType=DECIMAL},
            </if>
            <if test="reason != null" >
                reason = #{reason,jdbcType=VARCHAR},
            </if>
        </set>
        where id = #{detail_id,jdbcType=BIGINT}
    </update>
</mapper>
